pyjp/__init__.py
pyjp/cum.py
pyjp/html_parser.py
pyjp/main.py
pyjp/stack.py
pyjp-0.1.dist-info/LICENSE
pyjp-0.1.dist-info/METADATA
pyjp-0.1.dist-info/WHEEL
pyjp-0.1.dist-info/entry_points.txt
pyjp-0.1.dist-info/top_level.txt
pyjp-0.1.dist-info/RECORD
